TI_WS23-24/ti23_assignment_09/src/sr_latch.sv
module sr_latch( input logic i_r,
                 input logic i_s,
                 output logic o_q,
                 output logic o_qinv );

    assign o_q = ~( i_r | o_qinv ); //NOR-Gate for Q
    assign o_qinv = ~( o_q | i_s ); //NOR-Gate for Qinv  //crossover of the outputs after the nor 

endmodule

/*
 * SR-Latch can store on bit of information
 * has 2 Inputs: S (Set) and R (Reset) --> internal state
 * output Q shows if internal state is SET to true (1) or RESET to false (0)
 * negated output Q is often left out 
*/

TI_WS23-24/ti23_assignment_09/src/d_latch.sv
module d_latch( input logic i_d,
                input logic i_clk,
                output logic o_q,
                output logic o_qinv);

    logic l_r, //l_r = output of and1 going into SR-Latch input R
          l_s, //L_s = output of and2 going into SR-Latch input S
          l_d_not;
   
    assign l_d_not = ~i_d;
    assign l_r = i_clk & l_d_not; //RESET will be 1, if CLK is 1 an 
    assign l_s = i_clk & i_d; //SET will be 1, if CLK is 1 and D is 1

    sr_latch sr_latch(.i_r(l_r), .i_s(l_s), .o_q(o_q), .o_qinv(o_qinv));
endmodule


/* 
 * D-Latch can store one bit information 
 * If Clock Signal is 1 (high), then set D as Output 
 * Otherwise the output is the output
*/

TI_WS23-24/ti23_assignment_09/src/d_latch_tb.sv
module d_latch_tb;
    logic l_d, 
          l_clk, 
          l_q, 
          l_qinv;

    d_latch m_dut(.i_d(l_d), .i_clk(l_clk), .o_q(l_q), .o_qinv(l_qinv));

    // Clock
    always begin
        l_clk <= 1'b1;
        #5;
        l_clk <= 1'b0;
        #5;
    end

    initial begin
        $dumpfile("dump_d_latch_tb.vcd");
        $dumpvars;

        //CLK is 0 --> nothing gets set doesnt matter what D is 
        l_d = 1'b0;
        #6;
        assert( l_q === 1'b0 );
        assert( l_qinv === 1'b1 );

        //CLK is 1 and D is 1 --> SET
        l_d = 1'b1;
        #6; //#12
        assert( l_q === 1'b1 );
        assert( l_qinv === 1'b0 );
        
        //CLK is 0 and D is 0 --> no changes, previous output
        #5; //#17
        l_d = 1'b0;
        assert( l_q === 1'b1 );
        assert( l_qinv === 1'b0 );
        
        //CLK is 1 and now D gets read and is 0 --> RESET (0,1)
        #7; //#23
        assert( l_q === 1'b0 );
        assert( l_qinv === 1'b1 );

        //CLK is 1 and D is 1 --> SET (1,0) --> as Result Q
        l_d = 1'b1;
        #11 //#33
        assert( l_q === 1'b1 );
        assert( l_qinv === 1'b0 );

        $finish;
    end
endmodule

TI_WS23-24/ti23_assignment_09_Alabrsh_Panov_Zeitler/src/dump_d_latch_tb.vcd
$date
	Sat Dec 16 04:07:48 2023
$end
$version
	Icarus Verilog
$end
$timescale
	1s
$end
$scope module d_latch_tb $end
$var wire 1 ! l_qinv $end
$var wire 1 " l_q $end
$var reg 1 # l_clk $end
$var reg 1 $ l_d $end
$scope module m_dut $end
$var wire 1 # i_clk $end
$var wire 1 $ i_d $end
$var wire 1 % l_d_not $end
$var wire 1 & l_r $end
$var wire 1 ' l_s $end
$var wire 1 ! o_qinv $end
$var wire 1 " o_q $end
$scope module sr_latch $end
$var wire 1 & i_r $end
$var wire 1 ' i_s $end
$var wire 1 " o_q $end
$var wire 1 ! o_qinv $end
$upscope $end
$upscope $end
$upscope $end
$enddefinitions $end
$comment Show the parameter values. $end
$dumpall
$end
#0
$dumpvars
0'
1&
1%
0$
1#
0"
1!
$end
#5
0&
0#
#6
0%
1$
#10
1"
0!
1'
1#
#15
0'
0#
#17
1%
0$
#20
1!
0"
1&
1#
#24
1"
0!
0&
0%
1'
1$
#25
0'
0#
#30
1'
1#
#35
0'
0#
