TI_WS23-24/ti23_assignment_09/src/sr_latch.sv
module sr_latch( input logic i_r,
                 input logic i_s,
                 output logic o_q,
                 output logic o_qinv );

    assign o_q = ~( i_r | o_qinv ); //NOR-Gate for Q
    assign o_qinv = ~( o_q | i_s ); //NOR-Gate for Qinv  //crossover of the outputs after the nor 

endmodule

/*
 * SR-Latch can store on bit of information
 * has 2 Inputs: S (Set) and R (Reset) --> internal state
 * output Q shows if internal state is SET to true (1) or RESET to false (0)
 * negated output Q is often left out 
*/

TI_WS23-24/ti23_assignment_09/src/d_latch.sv
module d_latch( input logic i_d,
                input logic i_clk,
                output logic o_q,
                output logic o_qinv);

    logic l_r, //l_r = output of and1 going into SR-Latch input R
          l_s, //L_s = output of and2 going into SR-Latch input S
          l_d_not;
   
    assign l_d_not = ~i_d;
    assign l_r = i_clk & l_d_not; //RESET will be 1, if CLK is 1 an 
    assign l_s = i_clk & i_d; //SET will be 1, if CLK is 1 and D is 1

    sr_latch sr_latch(.i_r(l_r), .i_s(l_s), .o_q(o_q), .o_qinv(o_qinv));
endmodule


/* 
 * D-Latch can store one bit information 
 * If Clock Signal is 1 (high), then set D as Output 
 * Otherwise the output is the output
*/

TI_WS23-24/ti23_assignment_10/src/d_flip_flop.sv
module d_flip_flop( input logic i_d,
                    input logic i_clk,
                    output logic o_q,
                    output logic o_qinv);

    logic l_clk_not, l_q_out, l_qinv_out;
    
    assign l_clk_not = ~i_clk; //iverted CLK Signal for first D-Latch
   
    d_latch d_latch_1(.i_clk(l_clk_not), .i_d(i_d), .o_q(l_q_out), .o_qinv(l_qinv_out));
                         
    d_latch d_latch_2(.i_clk(i_clk), .i_d(l_q_out), .o_q(o_q), .o_qinv(o_qinv));
                                           
endmodule

/*
 * D-FlipFlop stores one bit information 
 * it has 2 Inputs: Data (D) and ClockSignal (CLK)
 * the outputs Q and -Q match with the value of the internal state
 * internal state is set to the data signal D, whenever CLK changes from LOW to HIGH --> rising edge triggered
 * Output gets set 1, if D is 1 and there is a rising edge after or at the same time 
*/

TI_WS23-24/ti23_assignment_09/src/d_flip_flop_tb.sv
module d_flip_flop_tb;
    logic l_d, 
          l_clk, 
          l_q,
          l_qinv;

    // Clock
    always begin
        l_clk <= 1'b1;
        #5;
        l_clk <= 1'b0;
        #5;
    end

    d_flip_flop m_dut(.i_clk(l_clk), .i_d(l_d), .o_q(l_q), .o_qinv(l_qinv));

    initial begin
        $dumpfile("dump_d_flip_flop_tb.vcd");
        $dumpvars;

        //testbench data from example waveform in lesson

        //clk is 1 and and d is 0 in de bgeinning
        #0
        l_d = 1'b0;

        //clk is already 1 and after #2 d is 1 
        //q is 0, cuz there was no rising edge
        #12;
        l_d = 1'b1;
        assert( l_q === 1'b0 );
        assert( l_qinv === 1'b1 );

        //clk is still 1 and d goes back to 0 
        // q is 0, cuz d is 0 befor rising edge 
        #1; 
        l_d = 1'b0;
        assert( l_q === 1'b0 );
        assert( l_qinv === 1'b1 );

        //#22: clk is already 1 and after #2 d is 1 
        //q is 0, cuz there was no rising edge --> rising edge was befor d got 1
        #9;
        l_d = 1'b1;
        assert( l_q === 1'b0 );
        assert( l_qinv === 1'b1 );
        
        //#27: clk is 0 and d is 0 -> q is 0, cuz no rising edge 
        #5;
        l_d = 1'b0;
        assert( l_q === 1'b0 );
        assert( l_qinv === 1'b1 );

        //#28: clk is still 0 and d is 1
        //q is 1, cuz after d gets 1, the clk will get 1 #31, an rising edge
        #1
        l_d = 1'b1;
        #3 //#31
        assert( l_q === 1'b1 );
        assert( l_qinv === 1'b0 );
        
        //#33: clk is 1 and d is 0
        // q is 1, cuz there is no rising edge after d is 0, so it doesnt change
        #2
        l_d = 1'b0;
        assert( l_q === 1'b1 );
        assert( l_qinv === 1'b0 );

        //#38: clk is still 0 and d is 1 
        // q is 1 again, cuz clk turns 1 after, an rising edge (no change, cuz it was 1 already)
        #5;
        l_d = 1'b1;
        assert( l_q === 1'b1 );
        assert( l_qinv === 1'b0 );

        //if d would be 0 in last testexaple, q would be 0, cuz of rising edge after

        $finish;
    end
endmodule

TI_WS23-24/ti23_assignment_09_Alabrsh_Panov_Zeitler/src/dump_d_flip_flop_tb.vcd
$date
	Sat Dec 16 19:31:53 2023
$end
$version
	Icarus Verilog
$end
$timescale
	1s
$end
$scope module d_flip_flop_tb $end
$var wire 1 ! l_qinv $end
$var wire 1 " l_q $end
$var reg 1 # l_clk $end
$var reg 1 $ l_d $end
$scope module m_dut $end
$var wire 1 # i_clk $end
$var wire 1 $ i_d $end
$var wire 1 % l_clk_not $end
$var wire 1 ! o_qinv $end
$var wire 1 " o_q $end
$var wire 1 & l_qinv_out $end
$var wire 1 ' l_q_out $end
$scope module d_latch_1 $end
$var wire 1 % i_clk $end
$var wire 1 $ i_d $end
$var wire 1 ( l_d_not $end
$var wire 1 ) l_r $end
$var wire 1 * l_s $end
$var wire 1 & o_qinv $end
$var wire 1 ' o_q $end
$scope module sr_latch $end
$var wire 1 ) i_r $end
$var wire 1 * i_s $end
$var wire 1 ' o_q $end
$var wire 1 & o_qinv $end
$upscope $end
$upscope $end
$scope module d_latch_2 $end
$var wire 1 # i_clk $end
$var wire 1 ' i_d $end
$var wire 1 + l_d_not $end
$var wire 1 , l_r $end
$var wire 1 - l_s $end
$var wire 1 ! o_qinv $end
$var wire 1 " o_q $end
$scope module sr_latch $end
$var wire 1 , i_r $end
$var wire 1 - i_s $end
$var wire 1 " o_q $end
$var wire 1 ! o_qinv $end
$upscope $end
$upscope $end
$upscope $end
$upscope $end
$enddefinitions $end
$comment Show the parameter values. $end
$dumpall
$end
#0
$dumpvars
x-
x,
x+
0*
0)
1(
x'
x&
0%
0$
1#
x"
x!
$end
#5
1&
1+
0'
1)
1%
0,
0-
0#
#10
1!
0"
0)
0%
1,
1#
#12
0(
1$
#13
1(
0$
#15
1)
1%
0,
0#
#20
0)
0%
1,
1#
#22
0(
1$
#25
0+
1'
0&
1*
1%
0,
0#
#27
1&
1+
0'
1)
1(
0*
0$
#28
0+
1'
0&
0)
0(
1*
1$
#30
1"
0!
0*
0%
1-
1#
#33
1(
0$
#35
1&
1+
0'
1)
1%
0-
0#
#38
0+
1'
0&
0)
0(
1*
1$
