TI_WS23-24/ti23_assignment_09_Alabrsh_Panov_Zeitler/src/mux_2.sv
module mux_2 #(parameter N=64) (input  logic [N-1:0] i_in0,
                                                     i_in1,
                                input  logic         i_s,
                                output logic [N-1:0] o_out );

    assign o_out = i_s ? i_in1: i_in0;

endmodule

TI_WS23-24/ti23_assignment_09/src/sr_latch.sv
module sr_latch( input logic i_r,
                 input logic i_s,
                 output logic o_q,
                 output logic o_qinv );

    assign o_q = ~( i_r | o_qinv ); //NOR-Gate for Q
    assign o_qinv = ~( o_q | i_s ); //NOR-Gate for Qinv  //crossover of the outputs after the nor 

endmodule

/*
 * SR-Latch can store on bit of information
 * has 2 Inputs: S (Set) and R (Reset) --> internal state
 * output Q shows if internal state is SET to true (1) or RESET to false (0)
 * negated output Q is often left out 
*/

TI_WS23-24/ti23_assignment_09/src/d_latch.sv
module d_latch( input logic i_d,
                input logic i_clk,
                output logic o_q,
                output logic o_qinv);

    logic l_r, //l_r = output of and1 going into SR-Latch input R
          l_s, //L_s = output of and2 going into SR-Latch input S
          l_d_not;
   
    assign l_d_not = ~i_d;
    assign l_r = i_clk & l_d_not; //RESET will be 1, if CLK is 1 an 
    assign l_s = i_clk & i_d; //SET will be 1, if CLK is 1 and D is 1

    sr_latch sr_latch(.i_r(l_r), .i_s(l_s), .o_q(o_q), .o_qinv(o_qinv));
endmodule


/* 
 * D-Latch can store one bit information 
 * If Clock Signal is 1 (high), then set D as Output 
 * Otherwise the output is the output
*/

TI_WS23-24/ti23_assignment_10/src/d_flip_flop.sv
module d_flip_flop( input logic i_d,
                    input logic i_clk,
                    output logic o_q,
                    output logic o_qinv);

    logic l_clk_not, l_q_out, l_qinv_out;
    
    assign l_clk_not = ~i_clk; //iverted CLK Signal for first D-Latch
   
    d_latch d_latch_1(.i_clk(l_clk_not), .i_d(i_d), .o_q(l_q_out), .o_qinv(l_qinv_out));
                         
    d_latch d_latch_2(.i_clk(i_clk), .i_d(l_q_out), .o_q(o_q), .o_qinv(o_qinv));
                                           
endmodule

/*
 * D-FlipFlop stores one bit information 
 * it has 2 Inputs: Data (D) and ClockSignal (CLK)
 * the outputs Q and -Q match with the value of the internal state
 * internal state is set to the data signal D, whenever CLK changes from LOW to HIGH --> rising edge triggered
 * Output gets set 1, if D is 1 and there is a rising edge after or at the same time 
*/

TI_WS23-24/ti23_assignment_09_Alabrsh_Panov_Zeitler/src/d_flip_flop_en.sv
module d_flip_flop_en( input logic i_d,
                       input logic i_en,
                       input logic i_clk,
                       output logic o_q);
    logic l_d_out;

    assign l_d_out = i_en ? i_d : o_q; //checking if EN is set --> if set: D is Input, else: previous output

    d_flip_flop d_flip_flop(.i_d(l_d_out), .i_clk(i_clk), .o_q(o_q));
                                                   
endmodule

/*
 * Enabled FlipFlop is a D FlipFlop with an enabled signal EN 
 * EN allows to set input D individually 
 * D will only be set if EN is 1
 * if D is enabled, Output will be D when rising edge, else output
*/

TI_WS23-24/ti23_assignment_09/src/d_flip_flop_en_tb.sv
// Testbench für das EN D-Flip-Flop
module d_flip_flop_en_tb;
    logic l_en, l_clk, l_d, l_q;

    d_flip_flop_en m_dut(.i_en(l_en), .i_clk(l_clk), .i_d(l_d), .o_q(l_q));

    always begin
        l_clk <= 1'b1;
        #5;
        l_clk <= 1'b0;
        #5;
    end

    initial begin
        $dumpfile("dump_d_flip_flop_en_tb.vcd");
        $dumpvars;

        //D is 1 and EN is 1, and there will be a rising edge, cuz clk will be 1 --> Q is 1
        #7;
        l_en = 1'b1;
        l_d = 1'b1;
        #6;
        assert( l_q === 1'b1 );

        //#16: D is 0 and EN stil 0, after #22 clk is 1 (rising edge) --> Q is 0, cuz D is 0
        #3; 
        l_en = 1'b1;
        l_d = 1'b0;
        #7; //#22
        assert( l_q === 1'b0 );

        //#23: D is 1 and EN is 0 --> Q is 0 because EN is 0 (previous result will be set) --> #32 is clk 1 (rising edge)
        #1; 
        l_en = 1'b0;
        l_d = 1'b1;
        #9; //#32
        assert( l_q === 1'b0 );

        //37: EN is 1 --> Q is 1, because D was 1 before and #42 is clk 1 
        #5; 
        l_en = 1'b1;
        #5; // '42
        assert( l_q === 1'b1 );
        $finish;
    end

endmodule

TI_WS23-24/ti23_assignment_09_Alabrsh_Panov_Zeitler/src/dump_d_flip_flop_en_tb.vcd
$date
	Sat Dec 16 04:34:49 2023
$end
$version
	Icarus Verilog
$end
$timescale
	1s
$end
$scope module d_flip_flop_en_tb $end
$var wire 1 ! l_q $end
$var reg 1 " l_clk $end
$var reg 1 # l_d $end
$var reg 1 $ l_en $end
$scope module m_dut $end
$var wire 1 " i_clk $end
$var wire 1 # i_d $end
$var wire 1 $ i_en $end
$var wire 1 ! o_q $end
$var wire 1 % l_d_out $end
$scope module d_flip_flop $end
$var wire 1 " i_clk $end
$var wire 1 % i_d $end
$var wire 1 & l_clk_not $end
$var wire 1 ' o_qinv $end
$var wire 1 ! o_q $end
$var wire 1 ( l_qinv_out $end
$var wire 1 ) l_q_out $end
$scope module d_latch_1 $end
$var wire 1 & i_clk $end
$var wire 1 % i_d $end
$var wire 1 * l_d_not $end
$var wire 1 + l_r $end
$var wire 1 , l_s $end
$var wire 1 ( o_qinv $end
$var wire 1 ) o_q $end
$scope module sr_latch $end
$var wire 1 + i_r $end
$var wire 1 , i_s $end
$var wire 1 ) o_q $end
$var wire 1 ( o_qinv $end
$upscope $end
$upscope $end
$scope module d_latch_2 $end
$var wire 1 " i_clk $end
$var wire 1 ) i_d $end
$var wire 1 - l_d_not $end
$var wire 1 . l_r $end
$var wire 1 / l_s $end
$var wire 1 ' o_qinv $end
$var wire 1 ! o_q $end
$scope module sr_latch $end
$var wire 1 . i_r $end
$var wire 1 / i_s $end
$var wire 1 ! o_q $end
$var wire 1 ' o_qinv $end
$upscope $end
$upscope $end
$upscope $end
$upscope $end
$upscope $end
$scope module mux_2 $end
$var wire 64 0 i_in0 [63:0] $end
$var wire 64 1 i_in1 [63:0] $end
$var wire 1 2 i_s $end
$var wire 64 3 o_out [63:0] $end
$var parameter 32 4 N $end
$upscope $end
$enddefinitions $end
$comment Show the parameter values. $end
$dumpall
b1000000 4
$end
#0
$dumpvars
bz 3
z2
bz 1
bz 0
x/
x.
x-
0,
0+
x*
x)
x(
x'
0&
x%
x$
x#
1"
x!
$end
#5
x+
x,
1&
0.
0/
0"
#7
0-
1)
0(
0+
0*
1,
1%
1#
1$
#10
1!
0'
0,
0&
1/
1"
#15
1,
1&
0/
0"
#16
1(
1-
0)
1+
1*
0,
0%
0#
#20
1'
0!
0+
0&
1.
1"
#24
1#
0$
#25
1+
1&
0.
0"
#30
0+
0&
1.
1"
#35
1+
1&
0.
0"
#38
0-
1)
0(
0+
0*
1,
1%
1$
#40
1!
0'
0,
0&
1/
1"
