TI_WS23-24/ti23_assignment_06/src/test.sv
module test(

   input logic x0,
   input logic x1,
   input logic x2, 
   output logic y0,
   output logic y1 
   
   );

   logic and1, and2;
   logic or1, or2;
   logic not1, not2, not3, not4, not5;

   assign not1 = ~x0;
   assign not2 = ~x2;
   assign not3 = ~x0;
   assign not4 = ~or1;
   assign not5 = ~or2;
   assign and1 = not1 & x1;
   assign or1 = ~x0 & ~x1;
   assign or2 = ~or1 | and1;
   assign and2 = x2 & or2;
   assign y0 = and2;
   assign y1 = not5;

endmodule

TI_WS23-24/ti23_assignment_06_Alabrsh_Panov_Zeitler/src/test_tb.sv
module test_tb;
//input 
logic x0;
logic x1;
logic x2;

//output
logic y0;
logic y1;

test dut(x0, x1, x2, y0, y1);

initial begin
    $dumpfile("dump_test.vcd");
    $dumpvars;
   
    //000
    x2 = 1'b0;
    x1 = 1'b0;
    x0 = 1'b0;
    #20;

    //001
    x2 = 1'b0;
    x1 = 1'b0;
    x0 = 1'b1;
    #20;


    //010
    x2 = 1'b0;
    x1 = 1'b1;
    x0 = 1'b0;
    #20;


    //011
    x2 = 1'b0;
    x1 = 1'b1;
    x0 = 1'b1;
    #20;

    //100
    x2 = 1'b1;
    x1 = 1'b0;
    x0 = 1'b0;
    #20;


    //101
    x2 = 1'b1;
    x1 = 1'b0;
    x0 = 1'b1;
    #20;


    //110
    x2 = 1'b1;
    x1 = 1'b1;
    x0 = 1'b0;
    #20;

    //111
    x2 = 1'b1;
    x1 = 1'b1;
    x0 = 1'b1;
    #20;

    $finish;

    
end
endmodule

TI_WS23-24/ti23_assignment_06/src/dump_test.vcd
$date
	Mon Nov 27 00:01:25 2023
$end
$version
	Icarus Verilog
$end
$timescale
	1s
$end
$scope module test_tb $end
$var wire 1 ! y1 $end
$var wire 1 " y0 $end
$var reg 1 # x0 $end
$var reg 1 $ x1 $end
$var reg 1 % x2 $end
$scope module dut $end
$var wire 1 & and1 $end
$var wire 1 ' and2 $end
$var wire 1 ( not1 $end
$var wire 1 ) not2 $end
$var wire 1 * not3 $end
$var wire 1 + not4 $end
$var wire 1 , not5 $end
$var wire 1 - or1 $end
$var wire 1 . or2 $end
$var wire 1 # x0 $end
$var wire 1 $ x1 $end
$var wire 1 % x2 $end
$var wire 1 " y0 $end
$var wire 1 ! y1 $end
$upscope $end
$upscope $end
$enddefinitions $end
#0
$dumpvars
0.
1-
1,
0+
1*
1)
1(
0'
0&
0%
0$
0#
0"
1!
$end
#20
0!
0,
1.
1+
0-
0(
0*
1#
#40
1&
1(
1*
0#
1$
#60
0&
0(
0*
1#
#80
1!
1,
0.
0+
1-
1(
1*
0)
0"
0'
0#
0$
1%
#100
1"
1'
0!
0,
1.
1+
0-
0(
0*
1#
#120
1&
1(
1*
0#
1$
#140
0&
0(
0*
1#
