TI_WS23-24/ti23_assignment_08_Alabrsh_Panov_Zeitler/src/xor_3.sv
// TODO: FInish the iplemetation od the module
// such that it computes the XOR of the three inputs.
// Namely, the output has the value of 1 
// if an odd number of the three inputs has value 1,
// otherwise, the output has the value 0.

module xor_3 ( input logic i_in0,
                           i_in1,
                           i_in2,
               output logic o_res );

    assign o_res = i_in0 ^ i_in1 ^ i_in2;
    
endmodule

TI_WS23-24/ti23_assignment_08_Alabrsh_Panov_Zeitler/src/xor_3_tb.sv
module xor3_tb;

    logic l_in0, 
          l_in1, 
          l_in2, 
          l_o;

    xor_3 dut(.i_in0(l_in0), .i_in1(l_in1), .i_in2(l_in2), .o_res(l_o));

    initial begin
        $dumpfile("dump_xor_3.vcd");
        $dumpvars;

        // 000 
        l_in0 = 1'b0;
        l_in1 = 1'b0;
        l_in2 = 1'b0;
        #10;
        assert(l_o === 1'b0);

        // 001 
        l_in0 = 1'b0;
        l_in1 = 1'b0;
        l_in2 = 1'b1;
        #10;
        assert(l_o === 1'b1);

        // 010 
        l_in0 = 1'b0;
        l_in1 = 1'b1;
        l_in2 = 1'b0;
        #10;
        assert(l_o === 1'b1);

        // 011 
        l_in0 = 1'b0;
        l_in1 = 1'b1;
        l_in2 = 1'b1;
        #10;
        assert(l_o === 1'b0);

        // 100 
        l_in0 = 1'b1;
        l_in1 = 1'b0;
        l_in2 = 1'b0;
        #10;
        assert(l_o === 1'b1);

        // 101 
        l_in0 = 1'b1;
        l_in1 = 1'b0;
        l_in2 = 1'b1;
        #10;
        assert(l_o === 1'b0);

        // 110 
        l_in0 = 1'b1;
        l_in1 = 1'b1;
        l_in2 = 1'b0;
        #10;
        assert(l_o === 1'b0);

        // 111 
        l_in0 = 1'b1;
        l_in1 = 1'b1;
        l_in2 = 1'b1;
        #10;
        assert(l_o === 1'b1);

        $finish;
        
    end
endmodule

TI_WS23-24/ti23_assignment_08/src/dump_xor_3.vcd
$date
	Fri Dec  8 17:14:38 2023
$end
$version
	Icarus Verilog
$end
$timescale
	1s
$end
$scope module xor3_tb $end
$var wire 1 ! l_o $end
$var reg 1 " l_in0 $end
$var reg 1 # l_in1 $end
$var reg 1 $ l_in2 $end
$scope module dut $end
$var wire 1 " i_in0 $end
$var wire 1 # i_in1 $end
$var wire 1 $ i_in2 $end
$var wire 1 ! o_res $end
$upscope $end
$upscope $end
$enddefinitions $end
#0
$dumpvars
0$
0#
0"
0!
$end
#10
1!
1$
#20
0$
1#
#30
0!
1$
#40
1!
0$
0#
1"
#50
0!
1$
#60
0$
1#
#70
1!
1$
