TI_WS23-24/ti23_assignment_06_Alabrsh_Panov_Zeitler/src/glitch.sv
module glitch(
   input logic x0,
   input logic x1,
   input logic x2, 
   output logic y0,
   output logic y1 
   );

   logic and1, and2;
   logic or1, or2;
   logic not1, not2, not3, not4, not5;

   assign #3 not1 = ~x0;
   assign #3 not2 = ~x2;
   assign #3 not3 = ~x0;
   assign #3 not4 = ~or1;
   assign #3 not5 = ~or2;
   assign #3 and1 = not1 & x1;
   assign #3 or1 = ~x0 & ~x1;
   assign #3 or2 = ~or1 | and1;
   assign #3 and2 = x2 & or2;
   assign #3 y0 = and2;
   assign #3 y1 = not5;

endmodule

TI_WS23-24/ti23_assignment_06/src/glitch_tb.sv
module glitch_tb;
//input 
logic x0;
logic x1;
logic x2;

//output
logic y0;
logic y1;

glitch dut(x0, x1, x2, y0, y1);

initial begin
    $dumpfile("dump_glitch.vcd");
    $dumpvars;
   
    //000
    x2 = 1'b0;
    x1 = 1'b0;
    x0 = 1'b0;
    #20;

    //001
    x2 = 1'b0;
    x1 = 1'b0;
    x0 = 1'b1;
    #20;


    //010
    x2 = 1'b0;
    x1 = 1'b1;
    x0 = 1'b0;
    #20;


    //011
    x2 = 1'b0;
    x1 = 1'b1;
    x0 = 1'b1;
    #20;

    //100
    x2 = 1'b1;
    x1 = 1'b0;
    x0 = 1'b0;
    #20;


    //101
    x2 = 1'b1;
    x1 = 1'b0;
    x0 = 1'b1;
    #20;


    //110
    x2 = 1'b1;
    x1 = 1'b1;
    x0 = 1'b0;
    #20;

    //111
    x2 = 1'b1;
    x1 = 1'b1;
    x0 = 1'b1;
    #20;

    $finish;

    
end
endmodule

TI_WS23-24/ti23_assignment_06_Alabrsh_Panov_Zeitler/src/dump_glitch.vcd
$date
	Thu Nov 23 17:56:04 2023
$end
$version
	Icarus Verilog
$end
$timescale
	1s
$end
$scope module glitch_tb $end
$var wire 1 ! y1 $end
$var wire 1 " y0 $end
$var reg 1 # x0 $end
$var reg 1 $ x1 $end
$var reg 1 % x2 $end
$scope module dut $end
$var wire 1 & and1 $end
$var wire 1 ' and2 $end
$var wire 1 ( not1 $end
$var wire 1 ) not2 $end
$var wire 1 * not3 $end
$var wire 1 + not4 $end
$var wire 1 , not5 $end
$var wire 1 - or1 $end
$var wire 1 . or2 $end
$var wire 1 # x0 $end
$var wire 1 $ x1 $end
$var wire 1 % x2 $end
$var wire 1 " y0 $end
$var wire 1 ! y1 $end
$upscope $end
$upscope $end
$enddefinitions $end
#0
$dumpvars
x.
x-
x,
x+
x*
x)
x(
x'
x&
0%
0$
0#
x"
x!
$end
#3
1-
1(
1*
1)
0'
0&
#6
0.
0+
0"
#9
1,
#12
1!
#20
1#
#23
0-
0(
0*
#26
1.
1+
#29
0,
#32
0!
#40
0#
1$
#43
1(
1*
#46
1&
#60
1#
#63
0(
0*
#66
0&
#80
0#
0$
1%
#83
1-
1(
1*
0)
1'
#86
0.
0+
1"
#89
0'
1,
#92
0"
1!
#100
1#
#103
0-
0(
0*
#106
1.
1+
#109
1'
0,
#112
1"
0!
#120
0#
1$
#123
1(
1*
#126
1&
#140
1#
#143
0(
0*
#146
0&
