TI_WS23-24/ti23_assignment_09/src/sr_latch.sv
module sr_latch( input logic i_r,
                 input logic i_s,
                 output logic o_q,
                 output logic o_qinv );

    assign o_q = ~( i_r | o_qinv ); //NOR-Gate for Q
    assign o_qinv = ~( o_q | i_s ); //NOR-Gate for Qinv  //crossover of the outputs after the nor 

endmodule

/*
 * SR-Latch can store on bit of information
 * has 2 Inputs: S (Set) and R (Reset) --> internal state
 * output Q shows if internal state is SET to true (1) or RESET to false (0)
 * negated output Q is often left out 
*/

TI_WS23-24/ti23_assignment_09/src/d_latch.sv
module d_latch( input logic i_d,
                input logic i_clk,
                output logic o_q,
                output logic o_qinv);

    logic l_r, //l_r = output of and1 going into SR-Latch input R
          l_s, //L_s = output of and2 going into SR-Latch input S
          l_d_not;
   
    assign l_d_not = ~i_d;
    assign l_r = i_clk & l_d_not; //RESET will be 1, if CLK is 1 an 
    assign l_s = i_clk & i_d; //SET will be 1, if CLK is 1 and D is 1

    sr_latch sr_latch(.i_r(l_r), .i_s(l_s), .o_q(o_q), .o_qinv(o_qinv));
endmodule


/* 
 * D-Latch can store one bit information 
 * If Clock Signal is 1 (high), then set D as Output 
 * Otherwise the output is the output
*/

TI_WS23-24/ti23_assignment_10/src/d_flip_flop.sv
module d_flip_flop( input logic i_d,
                    input logic i_clk,
                    output logic o_q,
                    output logic o_qinv);

    logic l_clk_not, l_q_out, l_qinv_out;
    
    assign l_clk_not = ~i_clk; //iverted CLK Signal for first D-Latch
   
    d_latch d_latch_1(.i_clk(l_clk_not), .i_d(i_d), .o_q(l_q_out), .o_qinv(l_qinv_out));
                         
    d_latch d_latch_2(.i_clk(i_clk), .i_d(l_q_out), .o_q(o_q), .o_qinv(o_qinv));
                                           
endmodule

/*
 * D-FlipFlop stores one bit information 
 * it has 2 Inputs: Data (D) and ClockSignal (CLK)
 * the outputs Q and -Q match with the value of the internal state
 * internal state is set to the data signal D, whenever CLK changes from LOW to HIGH --> rising edge triggered
 * Output gets set 1, if D is 1 and there is a rising edge after or at the same time 
*/

TI_WS23-24/ti23_assignment_09_Alabrsh_Panov_Zeitler/src/d_flip_flop_en.sv
module d_flip_flop_en( input logic i_d,
                       input logic i_en,
                       input logic i_clk,
                       output logic o_q);
    logic l_d_out;

    assign l_d_out = i_en ? i_d : o_q; //checking if EN is set --> if set: D is Input, else: previous output

    d_flip_flop d_flip_flop(.i_d(l_d_out), .i_clk(i_clk), .o_q(o_q));
                                                   
endmodule

/*
 * Enabled FlipFlop is a D FlipFlop with an enabled signal EN 
 * EN allows to set input D individually 
 * D will only be set if EN is 1
 * if D is enabled, Output will be D when rising edge, else output
*/

TI_WS23-24/ti23_assignment_10/src/register_en_4.sv
module register_en_4( input  logic       i_clk,
                      input  logic       i_en,
                      input  logic [3:0] i_d,
                      output logic [3:0] o_q );
    
    d_flip_flop_en d_flip_flop_en1(.i_clk(i_clk), .i_en(i_en), .i_d(i_d[0]), .o_q(o_q[0]));
    d_flip_flop_en d_flip_flop_en2(.i_clk(i_clk), .i_en(i_en), .i_d(i_d[1]), .o_q(o_q[1]));
    d_flip_flop_en d_flip_flop_en3(.i_clk(i_clk), .i_en(i_en), .i_d(i_d[2]), .o_q(o_q[2]));
    d_flip_flop_en d_flip_flop_en4(.i_clk(i_clk), .i_en(i_en), .i_d(i_d[3]), .o_q(o_q[3]));

endmodule

/**
 * Allows to save/write and load/read 4bit of information at once
 * has 4bits of data input (d0 - d3)
 * has 4bits of data output (q0 -q3)
 * EN (enables) --> Boolean defining if current information at data input is saved
 * CLK --> to time saving/loading data
*/

TI_WS23-24/ti23_assignment_09/src/register_en_4_tb.sv
module register_en_4_tb;
    logic l_clk, 
          l_en;
    logic [3:0] l_d, 
                l_q;

    always begin
        l_clk <= 1'b1;
        #5;
        l_clk <= 1'b0;
        #5;
    end

    register_en_4 m_dut(.i_clk(l_clk), .i_en(l_en), .i_d(l_d), .o_q(l_q));
                              
    initial begin
        $dumpfile("dump_register_en_4_tb.vcd");
        $dumpvars;

        // clk is 0 and d is 0000 and en is 1 --> #14: clk is 1 and at rising edge(#10) q will be 0000
        #7;
        l_en = 1'b1;
        l_d = 4'b0000;
        #7; //#14
        assert( l_q === 4'b0000 );

        //#16: clk is 0, d is 0110 and en is 1 --> at next rising edge (#20): q will be 0110
        #2; 
        l_en = 1'b1;
        l_d = 4'b0110;
        #7; //#22
        assert( l_q === 4'b0110 );

        //#23: clk is 1, d is 1111 and en is 0 --> no changes, cuz en is 0, doesnt matter what d and clk is
        #1; 
        l_en = 1'b0;
        l_d = 4'b1111;
        #9; //#32
        assert( l_q === 4'b0110 );

        //#37: clk is 0 and en is 1 --> at next rising edge (#40), q will be 1111
        #5; 
        l_en = 1'b1;
        #5; //#42
        assert( l_q === 4'b1111 );

        $finish;
    end
endmodule

TI_WS23-24/ti23_assignment_10/src/dump/dump_register_en_4_tb.vcd
$date
	Sat Dec 16 19:52:24 2023
$end
$version
	Icarus Verilog
$end
$timescale
	1s
$end
$scope module register_en_4_tb $end
$var wire 4 ! l_q [3:0] $end
$var reg 1 " l_clk $end
$var reg 4 # l_d [3:0] $end
$var reg 1 $ l_en $end
$scope module m_dut $end
$var wire 1 " i_clk $end
$var wire 4 % i_d [3:0] $end
$var wire 1 $ i_en $end
$var wire 4 & o_q [3:0] $end
$scope module d_flip_flop_en1 $end
$var wire 1 " i_clk $end
$var wire 1 ' i_d $end
$var wire 1 $ i_en $end
$var wire 1 ( o_q $end
$var wire 1 ) l_d_out $end
$scope module d_flip_flop $end
$var wire 1 " i_clk $end
$var wire 1 ) i_d $end
$var wire 1 * l_clk_not $end
$var wire 1 + o_qinv $end
$var wire 1 ( o_q $end
$var wire 1 , l_qinv_out $end
$var wire 1 - l_q_out $end
$scope module d_latch_1 $end
$var wire 1 * i_clk $end
$var wire 1 ) i_d $end
$var wire 1 . l_d_not $end
$var wire 1 / l_r $end
$var wire 1 0 l_s $end
$var wire 1 , o_qinv $end
$var wire 1 - o_q $end
$scope module sr_latch $end
$var wire 1 / i_r $end
$var wire 1 0 i_s $end
$var wire 1 - o_q $end
$var wire 1 , o_qinv $end
$upscope $end
$upscope $end
$scope module d_latch_2 $end
$var wire 1 " i_clk $end
$var wire 1 - i_d $end
$var wire 1 1 l_d_not $end
$var wire 1 2 l_r $end
$var wire 1 3 l_s $end
$var wire 1 + o_qinv $end
$var wire 1 ( o_q $end
$scope module sr_latch $end
$var wire 1 2 i_r $end
$var wire 1 3 i_s $end
$var wire 1 ( o_q $end
$var wire 1 + o_qinv $end
$upscope $end
$upscope $end
$upscope $end
$upscope $end
$scope module d_flip_flop_en2 $end
$var wire 1 " i_clk $end
$var wire 1 4 i_d $end
$var wire 1 $ i_en $end
$var wire 1 5 o_q $end
$var wire 1 6 l_d_out $end
$scope module d_flip_flop $end
$var wire 1 " i_clk $end
$var wire 1 6 i_d $end
$var wire 1 7 l_clk_not $end
$var wire 1 8 o_qinv $end
$var wire 1 5 o_q $end
$var wire 1 9 l_qinv_out $end
$var wire 1 : l_q_out $end
$scope module d_latch_1 $end
$var wire 1 7 i_clk $end
$var wire 1 6 i_d $end
$var wire 1 ; l_d_not $end
$var wire 1 < l_r $end
$var wire 1 = l_s $end
$var wire 1 9 o_qinv $end
$var wire 1 : o_q $end
$scope module sr_latch $end
$var wire 1 < i_r $end
$var wire 1 = i_s $end
$var wire 1 : o_q $end
$var wire 1 9 o_qinv $end
$upscope $end
$upscope $end
$scope module d_latch_2 $end
$var wire 1 " i_clk $end
$var wire 1 : i_d $end
$var wire 1 > l_d_not $end
$var wire 1 ? l_r $end
$var wire 1 @ l_s $end
$var wire 1 8 o_qinv $end
$var wire 1 5 o_q $end
$scope module sr_latch $end
$var wire 1 ? i_r $end
$var wire 1 @ i_s $end
$var wire 1 5 o_q $end
$var wire 1 8 o_qinv $end
$upscope $end
$upscope $end
$upscope $end
$upscope $end
$scope module d_flip_flop_en3 $end
$var wire 1 " i_clk $end
$var wire 1 A i_d $end
$var wire 1 $ i_en $end
$var wire 1 B o_q $end
$var wire 1 C l_d_out $end
$scope module d_flip_flop $end
$var wire 1 " i_clk $end
$var wire 1 C i_d $end
$var wire 1 D l_clk_not $end
$var wire 1 E o_qinv $end
$var wire 1 B o_q $end
$var wire 1 F l_qinv_out $end
$var wire 1 G l_q_out $end
$scope module d_latch_1 $end
$var wire 1 D i_clk $end
$var wire 1 C i_d $end
$var wire 1 H l_d_not $end
$var wire 1 I l_r $end
$var wire 1 J l_s $end
$var wire 1 F o_qinv $end
$var wire 1 G o_q $end
$scope module sr_latch $end
$var wire 1 I i_r $end
$var wire 1 J i_s $end
$var wire 1 G o_q $end
$var wire 1 F o_qinv $end
$upscope $end
$upscope $end
$scope module d_latch_2 $end
$var wire 1 " i_clk $end
$var wire 1 G i_d $end
$var wire 1 K l_d_not $end
$var wire 1 L l_r $end
$var wire 1 M l_s $end
$var wire 1 E o_qinv $end
$var wire 1 B o_q $end
$scope module sr_latch $end
$var wire 1 L i_r $end
$var wire 1 M i_s $end
$var wire 1 B o_q $end
$var wire 1 E o_qinv $end
$upscope $end
$upscope $end
$upscope $end
$upscope $end
$scope module d_flip_flop_en4 $end
$var wire 1 " i_clk $end
$var wire 1 N i_d $end
$var wire 1 $ i_en $end
$var wire 1 O o_q $end
$var wire 1 P l_d_out $end
$scope module d_flip_flop $end
$var wire 1 " i_clk $end
$var wire 1 P i_d $end
$var wire 1 Q l_clk_not $end
$var wire 1 R o_qinv $end
$var wire 1 O o_q $end
$var wire 1 S l_qinv_out $end
$var wire 1 T l_q_out $end
$scope module d_latch_1 $end
$var wire 1 Q i_clk $end
$var wire 1 P i_d $end
$var wire 1 U l_d_not $end
$var wire 1 V l_r $end
$var wire 1 W l_s $end
$var wire 1 S o_qinv $end
$var wire 1 T o_q $end
$scope module sr_latch $end
$var wire 1 V i_r $end
$var wire 1 W i_s $end
$var wire 1 T o_q $end
$var wire 1 S o_qinv $end
$upscope $end
$upscope $end
$scope module d_latch_2 $end
$var wire 1 " i_clk $end
$var wire 1 T i_d $end
$var wire 1 X l_d_not $end
$var wire 1 Y l_r $end
$var wire 1 Z l_s $end
$var wire 1 R o_qinv $end
$var wire 1 O o_q $end
$scope module sr_latch $end
$var wire 1 Y i_r $end
$var wire 1 Z i_s $end
$var wire 1 O o_q $end
$var wire 1 R o_qinv $end
$upscope $end
$upscope $end
$upscope $end
$upscope $end
$upscope $end
$upscope $end
$enddefinitions $end
$comment Show the parameter values. $end
$dumpall
$end
#0
$dumpvars
xZ
xY
xX
0W
0V
xU
xT
xS
xR
0Q
xP
xO
xN
xM
xL
xK
0J
0I
xH
xG
xF
xE
0D
xC
xB
xA
x@
x?
x>
0=
0<
x;
x:
x9
x8
07
x6
x5
x4
x3
x2
x1
00
0/
x.
x-
x,
x+
0*
x)
x(
x'
bx &
bx %
x$
bx #
1"
bx !
$end
#5
x/
x0
x<
x=
xI
xJ
xV
xW
1*
02
03
17
0?
0@
1D
0L
0M
1Q
0Y
0Z
0"
#7
1,
19
1F
1S
11
1>
1K
1X
0-
0:
0G
0T
1/
1<
1I
1V
1.
00
1;
0=
1H
0J
1U
0W
0)
06
0C
0P
0'
04
0A
0N
b0 #
b0 %
1$
#10
1+
18
1E
1R
0(
05
0B
b0 !
b0 &
0O
0/
0<
0I
0V
0*
12
07
1?
0D
1L
0Q
1Y
1"
#15
1/
1<
1I
1V
1*
02
17
0?
1D
0L
1Q
0Y
0"
#16
0>
0K
1:
1G
09
0F
0<
0I
0;
1=
0H
1J
16
1C
14
1A
b110 #
b110 %
#20
15
b110 !
b110 &
1B
08
0E
0/
0=
0J
0V
0*
12
07
1@
0D
1M
0Q
1Y
1"
#24
1'
1N
b1111 #
b1111 %
0$
#25
1/
1=
1J
1V
1*
02
17
0@
1D
0M
1Q
0Y
0"
#30
0/
0=
0J
0V
0*
12
07
1@
0D
1M
0Q
1Y
1"
#35
1/
1=
1J
1V
1*
02
17
0@
1D
0M
1Q
0Y
0"
#38
01
0X
1-
1T
0,
0S
0/
0V
0.
10
0U
1W
1)
1P
1$
#40
1(
b1111 !
b1111 &
1O
0+
0R
00
0=
0J
0W
0*
13
07
1@
0D
1M
0Q
1Z
1"
